LICENSE
MANIFEST.in
README.md
requirements.txt
setup.py
doc/api.rst
doc/conf.py
doc/guide.rst
doc/index.rst
doc/installation.rst
doc/links.rst
doc/troubleshooting.rst
doc/img/favicon.ico
doc/img/logo.png
doc/img/rf_confusion_matrix.png
doc/img/svm_confusion_matrix.png
rrgp/__init__.py
rrgp/algorithm.py
rrgp/database.py
rrgp/evaluator.py
rrgp/preprocessor.py
rrgp/run.py
rrgp/tests.py
rrgp.egg-info/PKG-INFO
rrgp.egg-info/SOURCES.txt
rrgp.egg-info/dependency_links.txt
rrgp.egg-info/entry_points.txt
rrgp.egg-info/requires.txt
rrgp.egg-info/top_level.txt