Metadata-Version: 2.1
Name: rrgp
Version: 1.0.7
Summary: This project aims to train a model to recognise human activities (like walking, standing, or sitting) based on accelerometer and gyroscope data collected with a smartphone.
Home-page: https://github.com/patrickaudriaz/mini-project
Author: Geoffrey Raposo, Patrick Audriaz
Author-email: geoffrey@raposo.ch, audriazp@gmail.com
License: MIT
Platform: UNKNOWN
Classifier: Intended Audience :: Developers
Classifier: License :: OSI Approved :: MIT License
Classifier: Natural Language :: English
Classifier: Programming Language :: Python
Classifier: Programming Language :: Python :: 3
Classifier: Topic :: Software Development :: Libraries :: Python Modules
